mago/__init__.py
mago/mago.py
mago/template/clipart1872623.png
mago/template/index.html
mago/template/logs.html
mago/template/workers.html
mago/utils/__init__.py
mago/utils/collector.py
mago/utils/report_generator.py
mago/utils/traffic_manager.py
mago/utils/worker.py
mago-0.0.10.dist-info/LICENSE
mago-0.0.10.dist-info/METADATA
mago-0.0.10.dist-info/WHEEL
mago-0.0.10.dist-info/top_level.txt
mago-0.0.10.dist-info/RECORD
