Metadata-Version: 2.1
Name: mago
Version: 0.0.10
Summary: Open Source general testing framework
Author-email: Wookjin Jang <wookjinjang95@gmail.com>
Requires-Python: >=3.7
License-File: LICENSE
Requires-Dist: numpy
Requires-Dist: django
